this_cli-0.3.dist-info/METADATA
this_cli-0.3.dist-info/RECORD
this_cli-0.3.dist-info/WHEEL
this_cli-0.3.dist-info/entry_points.txt
this_cli-0.3.dist-info/top_level.txt
thiscli/__init__.py
thiscli/__main__.py
thiscli/click_colors.py
thiscli/env.py
thiscli/tmux.py
thiscli/util.py
thiscli/project/__init__.py
thiscli/project/ansible.py
thiscli/project/autotools.py
thiscli/project/cargo.py
thiscli/project/cmake.py
thiscli/project/dotnet.py
thiscli/project/gradle.py
thiscli/project/laravel.py
thiscli/project/make.py
thiscli/project/meson.py
thiscli/project/nodejs.py
thiscli/project/python.py
