Metadata-Version: 2.1
Name: this-cli
Version: 0.3
Summary: Standardized project tool for running common tasks
Home-page: https://github.com/ibelieve/this
Author: Michael Spencer
Author-email: sonrisesoftware@gmail.com
License: MIT
Platform: UNKNOWN
Requires-Dist: Click
